pytest_fixture_order/__init__.py
pytest_fixture_order/compat.py
pytest_fixture_order/plugin.py
pytest_fixture_order-0.1.2.dist-info/entry_points.txt
pytest_fixture_order-0.1.2.dist-info/WHEEL
pytest_fixture_order-0.1.2.dist-info/METADATA
pytest_fixture_order-0.1.2.dist-info/RECORD
